repotokens.py
repotokens-1.0.1.dist-info/LICENSE
repotokens-1.0.1.dist-info/METADATA
repotokens-1.0.1.dist-info/WHEEL
repotokens-1.0.1.dist-info/entry_points.txt
repotokens-1.0.1.dist-info/top_level.txt
repotokens-1.0.1.dist-info/RECORD
