Metadata-Version: 2.1
Name: repotokens
Version: 1.0.1
Summary: Count number of LLM tokens of source files contained in the repository / folder
Home-page: UNKNOWN
License: UNKNOWN
Platform: UNKNOWN
License-File: LICENSE
Requires-Dist: tiktoken
